LICENSE
MANIFEST.in
README.md
setup.py
django_test_toolkit/__init__.py
django_test_toolkit/testcases.py
django_test_toolkit.egg-info/PKG-INFO
django_test_toolkit.egg-info/SOURCES.txt
django_test_toolkit.egg-info/dependency_links.txt
django_test_toolkit.egg-info/not-zip-safe
django_test_toolkit.egg-info/requires.txt
django_test_toolkit.egg-info/top_level.txt
django_test_toolkit/data_generation/__init__.py
django_test_toolkit/data_generation/config.py
django_test_toolkit/data_generation/constants.py
django_test_toolkit/data_generation/faker_generator.py
django_test_toolkit/data_generation/field_processing_functions.py
django_test_toolkit/mixins/__init__.py
django_test_toolkit/mixins/account.py
django_test_toolkit/mixins/base.py
django_test_toolkit/mixins/blueking.py
django_test_toolkit/mixins/drf.py
tests/__init__.py
tests/manage.py
tests/settings.py
tests/data_generation/__init__.py
tests/data_generation/base.py
tests/data_generation/test_faker_generator.py
tests/data_generation/test_field_processing_functions.py
tests/django_test_app/__init__.py
tests/django_test_app/apps.py
tests/django_test_app/models.py
tests/django_test_app/migrations/0001_initial.py
tests/django_test_app/migrations/__init__.py
tests/life_cycle_hook/__init__.py
tests/life_cycle_hook/test_life_cycle_hook.py