Metadata-Version: 2.1
Name: django-test-toolkit
Version: 1.1.0
Summary: Toolkit for test based on Django
Home-page: https://github.com/TencentBlueKing/django-test-toolkit
Author: normal-wls
License: UNKNOWN
Platform: UNKNOWN
